srusp/__init__.py
srusp-0.1.0.dist-info/WHEEL
srusp-0.1.0.dist-info/METADATA
srusp-0.1.0.dist-info/RECORD
